scine_xtb_wrapper/LICENSE.txt
scine_xtb_wrapper/__init__.py
scine_xtb_wrapper/xtb.module.so
scine_xtb_wrapper.libs/libblas-fe34f726.so.3.8.0
scine_xtb_wrapper.libs/libboost_atomic-00e6ede8.so.1.78.0
scine_xtb_wrapper.libs/libboost_filesystem-e9e1d9ac.so.1.78.0
scine_xtb_wrapper.libs/libboost_system-c0fa27da.so.1.78.0
scine_xtb_wrapper.libs/libgfortran-83c28eba.so.5.0.0
scine_xtb_wrapper.libs/libgomp-e985bcbb.so.1.0.0
scine_xtb_wrapper.libs/liblapack-31d7d384.so.3.8.0
scine_xtb_wrapper.libs/libquadmath-2284e583.so.0.0.0
scine_xtb_wrapper-3.0.2.dist-info/METADATA
scine_xtb_wrapper-3.0.2.dist-info/WHEEL
scine_xtb_wrapper-3.0.2.dist-info/top_level.txt
scine_xtb_wrapper-3.0.2.dist-info/RECORD
